Workbook

Sheet Расчет прибыли на n-количество 
A1: Наименование | B1: Цена продажи 1 ед. | C1: Цена закупа 1 ед. | D1: Кол-во | E1: Прочие расходы | F1: Комиссия | G1: Логистика | H1: Хранение | I1: Прибыль | J1: Прибыль после вычета налогов (6%) | L1: Дневная ставка хранения
A2: Кошелек черный | B2: 990 | C2: 450 | D2: 1 | E2: ='Прочие расходы'!D2 -> 0 | F2: 0.1 | G2: 65 | H2: =$L$5*$L$2*D2 -> 3.5 | I2: =ROUND(((B2*D2)*(1-F2)-G2-(C2*D2)-H2-E2),0) -> 373 | J2: =ROUND(I2*(1-6%),0) -> 351 | L2: 0.07
A3: Обложка для паспорта | B3: 600 | C3: 200 | D3: 100 | E3: ='Прочие расходы'!D6 -> 0 | F3: 0.1 | G3: 55 | H3: =($L$5*$L$2)*D3 -> 350 | I3: =ROUND(((B3*D3)*(1-F3)-G3-(C3*D3)-H3-E3),0) -> 33595 | J3: =ROUND(I3*(1-6%),0) -> 31579
A4: Головные уборы | B4: 450 | C4: 150 | D4: 1 | E4: ='Прочие расходы'!D10 -> 0 | F4: 0.15 | H4: =$L$5*$L$2*D4 -> 3.5 | I4: =ROUND(((B4*D4)*(1-F4)-G4-(C4*D4)-H4-E4),0) -> 229 | J4: =ROUND(I4*(1-6%),0) -> 215 | L4: Кол-во дней хранения
E5: ='Прочие расходы'!D14 -> 0 | F5: 0.15 | H5: =($L$5*$L$2)*D5 -> 0 | I5: =ROUND(((B5*D5)*(1-F5)-G5-(C5*D5)-H5-E5),0) -> 0 | J5: =ROUND(I5*(1-6%),0) -> 0 | L5: 50
E6: ='Прочие расходы'!I2 -> 0 | H6: =$L$5*$L$2*D6 -> 0 | I6: =ROUND(((B6*D6)*(1-F6)-G6-(C6*D6)-H6-E6),0) -> 0 | J6: =ROUND(I6*(1-6%),0) -> 0
E7: ='Прочие расходы'!I6 -> 0 | H7: =($L$5*$L$2)*D7 -> 0 | I7: =ROUND(((B7*D7)*(1-F7)-G7-(C7*D7)-H7-E7),0) -> 0 | J7: =ROUND(I7*(1-6%),0) -> 0
E8: ='Прочие расходы'!I10 -> 0 | H8: =$L$5*$L$2*D8 -> 0 | I8: =ROUND(((B8*D8)*(1-F8)-G8-(C8*D8)-H8-E8),0) -> 0 | J8: =ROUND(I8*(1-6%),0) -> 0
E9: ='Прочие расходы'!I14 -> 0 | H9: =($L$5*$L$2)*D9 -> 0 | I9: =ROUND(((B9*D9)*(1-F9)-G9-(C9*D9)-H9-E9),0) -> 0 | J9: =ROUND(I9*(1-6%),0) -> 0
E10: ='Прочие расходы'!N2 -> 0 | H10: =$L$5*$L$2*D10 -> 0 | I10: =ROUND(((B10*D10)*(1-F10)-G10-(C10*D10)-H10-E10),0) -> 0 | J10: =ROUND(I10*(1-6%),0) -> 0 | L10: Данные в серых ячейках вычисляются автоматически, остальные ячейки редактируемые
E11: ='Прочие расходы'!N6 -> 0 | H11: =($L$5*$L$2)*D11 -> 0 | I11: =ROUND(((B11*D11)*(1-F11)-G11-(C11*D11)-H11-E11),0) -> 0 | J11: =ROUND(I11*(1-6%),0) -> 0
E12: ='Прочие расходы'!N10 -> 0 | H12: =$L$5*$L$2*D12 -> 0 | I12: =ROUND(((B12*D12)*(1-F12)-G12-(C12*D12)-H12-E12),0) -> 0 | J12: =ROUND(I12*(1-6%),0) -> 0
E13: ='Прочие расходы'!N14 -> 0 | H13: =($L$5*$L$2)*D13 -> 0 | I13: =ROUND(((B13*D13)*(1-F13)-G13-(C13*D13)-H13-E13),0) -> 0 | J13: =ROUND(I13*(1-6%),0) -> 0
E14: ='Прочие расходы'!N15 -> 0 | H14: =$L$5*$L$2*D14 -> 0 | I14: =ROUND(((B14*D14)*(1-F14)-G14-(C14*D14)-H14-E14),0) -> 0 | J14: =ROUND(I14*(1-6%),0) -> 0 | L14: В столбец "Логистика" вводятся расходы на всю партию. Данные в столбец "Прочие расход" подтягиваются автоматически и расчитываются на всю партию
E15: ='Прочие расходы'!N16 -> 0 | H15: =($L$5*$L$2)*D15 -> 0 | I15: =ROUND(((B15*D15)*(1-F15)-G15-(C15*D15)-H15-E15),0) -> 0 | J15: =ROUND(I15*(1-6%),0) -> 0
E16: ='Прочие расходы'!N17 -> 0 | H16: 3 | I16: =ROUND(((B16*D16)*(1-F16)-G16-(C16*D16)-H16-E16),0) -> -3 | J16: =ROUND(I16*(1-6%),0) -> -3
E17: ='Прочие расходы'!N18 -> 0 | H17: =($L$5*$L$2)*D17 -> 0 | I17: =ROUND(((B17*D17)*(1-F17)-G17-(C17*D17)-H17-E17),0) -> 0 | J17: =ROUND(I17*(1-6%),0) -> 0
E18: ='Прочие расходы'!N19 -> 0 | H18: =$L$5*$L$2*D18 -> 0 | I18: =ROUND(((B18*D18)*(1-F18)-G18-(C18*D18)-H18-E18),0) -> 0 | J18: =ROUND(I18*(1-6%),0) -> 0
E19: ='Прочие расходы'!N20 -> 0 | H19: =($L$5*$L$2)*D19 -> 0 | I19: =ROUND(((B19*D19)*(1-F19)-G19-(C19*D19)-H19-E19),0) -> 0 | J19: =ROUND(I19*(1-6%),0) -> 0
E20: ='Прочие расходы'!N21 -> 0 | I20: =ROUND(((B20*D20)*(1-F20)-G20-(C20*D20)-H20-E20),0) -> 0 | J20: =ROUND(I20*(1-6%),0) -> 0

Sheet Лист5

Sheet Прочие расходы
A1: Наименование товара | B1: Наименование расхода | C1: Цена | D1: Итого | F1: Наименование товара | G1: Наименование расхода | H1: Цена | I1: Итого | K1: Наименование товара | L1: Наименование расхода | M1: Цена | N1: Итого
A2: ='Расчет прибыли на n-количество '!A2 -> Кошелек черный | B2: упаковка | D2: =SUM(C2:C5) -> 0 | F2: ='Расчет прибыли на n-количество '!A6 -> 0 | G2: Расход 1 | I2: =SUM(H2:H5) -> 0 | K2: ='Расчет прибыли на n-количество '!A10 -> 0 | L2: Расход 1 | N2: =SUM(M2:M5) -> 0
G3: Расход 2 | L3: Расход 2
G4: Расход 3 | L4: Расход 3
G5: Расход 4 | L5: Расход 4
A6: ='Расчет прибыли на n-количество '!A3 -> Обложка для паспорта | B6: Расход 1 | D6: =SUM(C6:C9) -> 0 | F6: ='Расчет прибыли на n-количество '!A7 -> 0 | G6: Расход 1 | I6: =SUM(H6:H9) -> 0 | K6: ='Расчет прибыли на n-количество '!A11 -> 0 | L6: Расход 1 | N6: =SUM(M6:M9) -> 0
B7: Расход 2 | G7: Расход 2 | L7: Расход 2
B8: Расход 3 | G8: Расход 3 | L8: Расход 3
B9: Расход 4 | G9: Расход 4 | L9: Расход 4
A10: ='Расчет прибыли на n-количество '!A4 -> Головные уборы | B10: Расход 1 | D10: =SUM(C10:C13) -> 0 | F10: ='Расчет прибыли на n-количество '!A8 -> 0 | G10: Расход 1 | I10: =SUM(H10:H13) -> 0 | K10: ='Расчет прибыли на n-количество '!A12 -> 0 | L10: Расход 1 | N10: =SUM(M10:M13) -> 0
B11: Расход 2 | G11: Расход 2 | L11: Расход 2
B12: Расход 3 | G12: Расход 3 | L12: Расход 3
B13: Расход 4 | G13: Расход 4 | L13: Расход 4
A14: ='Расчет прибыли на n-количество '!A5 -> 0 | B14: Расход 1 | D14: =SUM(C14:C17) -> 0 | F14: ='Расчет прибыли на n-количество '!A9 -> 0 | G14: Расход 1 | I14: =SUM(H14:H17) -> 0 | K14: ='Расчет прибыли на n-количество '!A13 -> 0 | L14: Расход 1 | N14: =SUM(M14:M17) -> 0
B15: Расход 2 | G15: Расход 2 | L15: Расход 2
B16: Расход 3 | G16: Расход 3 | L16: Расход 3
B17: Расход 4 | G17: Расход 4 | L17: Расход 4

Sheet Лист6

Sheet Лист7
A1: Наименование | B1: Цена продажи 1 ед. | C1: Цена закупа 1 ед. | D1: Кол-во | E1: Прочие расходы | F1: Комиссия | G1: Логистика | H1: Хранение | I1: Прибыль | J1: Прибыль после вычета налогов (6%) | L1: Дневная ставка хранения
A2: турки | B2: 998 | C2: 550 | D2: 50 | E2: ='Прочие расходы'!D2 -> 0 | F2: 0.12 | G2: 55 | H2: =($L$5*$L$2)*D2 -> 105 | I2: =ROUND(((B2*D2)*(1-F2)-G2-(C2*D2)-H2-E2),0) -> 16252 | J2: =ROUND(I2*(1-6%),0) -> 15277 | L2: 0.07
A3: подогрев | B3: 650 | C3: 274 | D3: 60 | E3: ='Прочие расходы'!D6 -> 0 | F3: 0.12 | G3: 55 | H3: =($L$5*$L$2)*D3 -> 126 | I3: =ROUND(((B3*D3)*(1-F3)-G3-(C3*D3)-H3-E3),0) -> 17699 | J3: =ROUND(I3*(1-6%),0) -> 16637
A4: Брюки | B4: 5000 | C4: 462 | D4: 1 | E4: ='Прочие расходы'!D10 -> 0 | F4: 0.15 | G4: 50 | H4: =($L$5*$L$2)*D4 -> 2.1 | I4: =ROUND(((B4*D4)*(1-F4)-G4-(C4*D4)-H4-E4),0) -> 3736 | J4: =ROUND(I4*(1-6%),0) -> 3512 | L4: Кол-во дней хранения
A5: Товар 4 | B5: 3000 | C5: 214 | D5: 1 | E5: ='Прочие расходы'!D14 -> 0 | F5: 0.15 | G5: 50 | H5: =($L$5*$L$2)*D5 -> 2.1 | I5: =ROUND(((B5*D5)*(1-F5)-G5-(C5*D5)-H5-E5),0) -> 2284 | J5: =ROUND(I5*(1-6%),0) -> 2147 | L5: 30
A6: Товар 5 | B6: 4000 | C6: 300 | D6: 1 | E6: ='Прочие расходы'!I2 -> 0 | F6: 0.15 | G6: 50 | H6: =($L$5*$L$2)*D6 -> 2.1 | I6: =ROUND(((B6*D6)*(1-F6)-G6-(C6*D6)-H6-E6),0) -> 3048 | J6: =ROUND(I6*(1-6%),0) -> 2865
A7: Товар 6 | B7: 4000 | C7: 300 | D7: 4 | E7: ='Прочие расходы'!I6 -> 0 | F7: 0.15 | G7: 50 | H7: =($L$5*$L$2)*D7 -> 8.4 | I7: =ROUND(((B7*D7)*(1-F7)-G7-(C7*D7)-H7-E7),0) -> 12342 | J7: =ROUND(I7*(1-6%),0) -> 11601 | L7: Данные в серых ячейках вычисляются автоматически, остальные ячейки редактируемые
A8: Товар 7 | B8: 4000 | C8: 300 | D8: 5 | E8: ='Прочие расходы'!I10 -> 0 | F8: 0.15 | G8: 50 | H8: =($L$5*$L$2)*D8 -> 10.5 | I8: =ROUND(((B8*D8)*(1-F8)-G8-(C8*D8)-H8-E8),0) -> 15440 | J8: =ROUND(I8*(1-6%),0) -> 14514
A9: Товар 8 | B9: 4000 | C9: 300 | D9: 2 | E9: ='Прочие расходы'!I14 -> 0 | F9: 0.15 | G9: 50 | H9: =($L$5*$L$2)*D9 -> 4.2 | I9: =ROUND(((B9*D9)*(1-F9)-G9-(C9*D9)-H9-E9),0) -> 6146 | J9: =ROUND(I9*(1-6%),0) -> 5777
A10: Товар 9 | B10: 4000 | C10: 300 | D10: 3 | E10: ='Прочие расходы'!N2 -> 0 | F10: 0.15 | G10: 50 | H10: =($L$5*$L$2)*D10 -> 6.3 | I10: =ROUND(((B10*D10)*(1-F10)-G10-(C10*D10)-H10-E10),0) -> 9244 | J10: =ROUND(I10*(1-6%),0) -> 8689
A11: Товар 10 | B11: 4000 | C11: 300 | D11: 5 | E11: ='Прочие расходы'!N6 -> 0 | F11: 0.15 | G11: 50 | H11: =($L$5*$L$2)*D11 -> 10.5 | I11: =ROUND(((B11*D11)*(1-F11)-G11-(C11*D11)-H11-E11),0) -> 15440 | J11: =ROUND(I11*(1-6%),0) -> 14514 | L11: В столбец "Логистика" вводятся расходы на всю партию. Данные в столбец "Прочие расход" подтягиваются автоматически и расчитываются на всю партию
A12: Товар 11 | B12: 1500 | C12: 500 | D12: 1 | E12: ='Прочие расходы'!N10 -> 0 | F12: 0.15 | G12: 50 | H12: =($L$5*$L$2)*D12 -> 2.1 | I12: =ROUND(((B12*D12)*(1-F12)-G12-(C12*D12)-H12-E12),0) -> 723 | J12: =ROUND(I12*(1-6%),0) -> 680
A13: Товар 12 | C13: 500 | D13: 1 | E13: ='Прочие расходы'!N14 -> 0 | F13: 0.15 | G13: 50 | H13: =($L$5*$L$2)*D13 -> 2.1 | I13: =ROUND(((B13*D13)*(1-F13)-G13-(C13*D13)-H13-E13),0) -> -552 | J13: =ROUND(I13*(1-6%),0) -> -519

Sheet Лист4
